<DOMSymbolItem xmlns:xsi="http://www.w3.org/2001/XMLSchema-instance" xmlns="http://ns.adobe.com/xfl/2008/" name="Assets/Symbol 15" itemID="5bcd700a-00000132" lastModified="1540190218">
  <timeline>
    <DOMTimeline name="Symbol 15" layerDepthEnabled="true">
      <layers>
        <DOMLayer name="Layer_1" color="#00FFFF" current="true" isSelected="true">
          <frames>
            <DOMFrame index="0" keyMode="9728">
              <elements>
                <DOMShape>
                  <fills>
                    <FillStyle index="1">
                      <SolidColor color="#FFFFCC"/>
                    </FillStyle>
                  </fills>
                  <edges>
                    <Edge fillStyle1="1" edges="!364 983S2[264 981 110 999!110 999[-108 1024 -144 1026!-144 1026[-291 1038 -475 1030!-475 1030[-575 1026 -807 1006!-807 1006[-1467 948 -1794 888!-1794 888[-2337 787 -2728 586!-2728 586[-2790 554 -2824 531!-2824 531[-2874 495 -2901 454
!-2901 454[-2933 405 -2935 350!-2935 350[-2936 290 -2900 252!-2900 252[-2980 204 -3104 169!-3104 169[-3249 134 -3321 114!-3321 114[-3593 40 -3694 -107!-3694 -107[-3759 -201 -3744 -321!-3744 -321[-3728 -444 -3634 -495!-3634 -495[-3709
 -519 -3725 -612!-3725 -612[-3739 -700 -3690 -768!-3690 -768[-3646 -827 -3565 -865!-3565 -865[-3505 -892 -3410 -914!-3410 -914[-3167 -970 -2845 -992!-2845 -992[-2725 -1000 -2275 -1013!-2275 -1013[-2007 -1022 -1434 -1054!-1434 -1054[-884
 -1083 -593 -1092!-593 -1092[-125 -1107 454 -1098!454 -1098[829 -1092 1502 -1070!1502 -1070[2460 -1040 2902 -1024!2902 -1024[3122 -1013 3234 -993!3234 -993[3416 -960 3537 -878!3537 -878[3680 -782 3730 -611!3730 -611[3781 -432 3681 -308
!3681 -308[3613 -221 3426 -156!3426 -156[3217 -82 3150 -27!3150 -27[3089 23 3007 154!3007 154[2922 287 2866 336!2866 336[2788 406 2665 443!2665 443[2587 465 2434 487!2434 487[2269 509 2199 527!2199 527[2072 559 1990 622!1990 622[2009
 739 1913 848!1913 848[1832 943 1697 1000!1697 1000[1444 1112 1161 1100!1161 1100[1033 1094 761 1038!761 1038[503 985 364 983"/>
                    <Edge cubics="!364 983(;194,979 25,1014 -144,1026q364 983Q264 981q110 999Q-108 1024q-144 1026);"/>
                    <Edge cubics="!-144 1026(;-365,1044 -587,1025 -807,1006q-144 1026Q-291 1038q-475 1030Q-575 1026q-807 1006);"/>
                    <Edge cubics="!-807 1006(;-1465,948 -2141,888 -2728,586q-807 1006Q-1467 948q-1794 888Q-2337 787q-2728 586);"/>
                    <Edge cubics="!-2728 586(;-2793,553 -2860,515 -2901,454q-2728 586Q-2790 554q-2824 531Q-2874 495q-2901 454);"/>
                    <Edge cubics="!-2901 454(;-2942,393 -2950,305 -2900,252q-2901 454Q-2933 405q-2935 350Q-2936 290q-2900 252);"/>
                    <Edge cubics="!-2900 252(;-3028,177 -3177,154 -3321,114q-2900 252Q-2980 204q-3104 169Q-3249 134q-3321 114);"/>
                    <Edge cubics="!-3321 114(;-3462,76 -3611,14 -3694,-107q-3321 114Q-3593 40q-3694 -107);"/>
                    <Edge cubics="!-3694 -107(;-3777,-228 -3764,-425 -3634,-495q-3694 -107Q-3759 -201q-3744 -321Q-3728 -444q-3634 -495);"/>
                    <Edge cubics="!-3634 -495(;-3737,-529 -3754,-681 -3690,-768q-3634 -495Q-3709 -519q-3725 -612Q-3739 -700q-3690 -768);"/>
                    <Edge cubics="!-3690 -768(;-3626,-854 -3515,-890 -3410,-914q-3690 -768Q-3646 -827q-3565 -865Q-3505 -892q-3410 -914);"/>
                    <Edge cubics="!-3410 -914(;-3038,-1000 -2655,-1002 -2275,-1013q-3410 -914Q-3167 -970q-2845 -992Q-2725 -1000q-2275 -1013);"/>
                    <Edge cubics="!-2275 -1013(;-1714,-1032 -1154,-1075 -593,-1092q-2275 -1013Q-2007 -1022q-1434 -1054Q-884 -1083q-593 -1092);"/>
                    <Edge cubics="!-593 -1092(;105,-1113 802,-1093 1502,-1070q-593 -1092Q-125 -1107q454 -1098Q829 -1092q1502 -1070);"/>
                    <Edge cubics="!1502 -1070(;1968,-1056 2437,-1042 2902,-1024q1502 -1070Q2460 -1040q2902 -1024);"/>
                    <Edge cubics="!2902 -1024(;3124,-1014 3355,-1000 3537,-878q2902 -1024Q3122 -1013q3234 -993Q3416 -960q3537 -878);"/>
                    <Edge cubics="!3537 -878(;3720,-755 3819,-479 3681,-308q3537 -878Q3680 -782q3730 -611Q3781 -432q3681 -308);"/>
                    <Edge cubics="!3681 -308(;3555,-149 3305,-155 3150,-27q3681 -308Q3613 -221q3426 -156Q3217 -82q3150 -27);"/>
                    <Edge cubics="!3150 -27(;3031,72 2980,233 2866,336q3150 -27Q3089 23q3007 154Q2922 287q2866 336);"/>
                    <Edge cubics="!2866 336(;2632,544 2237,433 1990,622q2866 336Q2788 406q2665 443Q2587 465q2434 487Q2269 509q2199 527Q2072 559q1990 622);"/>
                    <Edge cubics="!1990 622(;2017,790 1856,932 1697,1000q1990 622Q2009 739q1913 848Q1832 943q1697 1000);"/>
                    <Edge cubics="!1697 1000(;1530,1075 1344,1107 1161,1100q1697 1000Q1444 1112q1161 1100);"/>
                    <Edge cubics="!1161 1100(;891,1087 632,988 364,983q1161 1100Q1033 1094q761 1038Q503 985q364 983);"/>
                  </edges>
                </DOMShape>
              </elements>
            </DOMFrame>
          </frames>
        </DOMLayer>
      </layers>
    </DOMTimeline>
  </timeline>
</DOMSymbolItem>